mtflow/__init__.py
mtflow/backfiller.py
mtflow/backtesting/backtest_history.py
mtflow/executor.py
mtflow/llm/literals.py
mtflow/llm/llm_plugin.py
mtflow/llm/prompt.py
mtflow/llm/registry.py
mtflow/llm/type.py
mtflow/monitor.py
mtflow/registry.py
mtflow/stores/base_data_store.py
mtflow/stores/market_data_store.py
mtflow/stores/mtstore.py
mtflow/stores/trading_store.py
mtflow/tracking/git_controller.py
mtflow/trading/_zmq_routes.py
mtflow/trading/mtengine.py
mtflow/trading/zeromq.py
mtflow/utils/utils.py
mtflow-0.0.1.dev2.dist-info/LICENSE
mtflow-0.0.1.dev2.dist-info/METADATA
mtflow-0.0.1.dev2.dist-info/WHEEL
mtflow-0.0.1.dev2.dist-info/RECORD
