Metadata-Version: 2.3
Name: mtflow
Version: 0.0.1.dev2
Summary: Machine Trading Lifecycle
License: Apache-2.0
Author: Stephen Yau
Author-email: softwareentrepreneer+mtflow@gmail.com
Requires-Python: >=3.10
Classifier: Operating System :: OS Independent
Classifier: Intended Audience :: Developers
Classifier: Intended Audience :: Science/Research
Classifier: Intended Audience :: Financial and Insurance Industry
Classifier: Intended Audience :: Information Technology
Classifier: Topic :: Office/Business :: Financial
Classifier: Topic :: Office/Business :: Financial :: Investment
Classifier: Topic :: Software Development :: Libraries
Classifier: Programming Language :: Python :: 3.10
Classifier: Programming Language :: Python :: 3.11
Classifier: Programming Language :: Python :: 3.12
Classifier: Programming Language :: Python :: 3.13
Provides-Extra: core
Requires-Dist: apscheduler (>=3.11.0,<4.0.0)
Requires-Dist: deepeval (>=2.6.5,<3.0.0) ; (python_version < "4.0.0") and (extra == "core")
Requires-Dist: gitpython (>=3.1.44,<4.0.0)
Requires-Dist: ipython (>=8.23.0,<9.0.0)
Requires-Dist: joblib (>=1.4.2,<2.0.0)
Requires-Dist: mlflow (>=2.21.3,<3.0.0)
Requires-Dist: optuna (>=4.2.1,<5.0.0)
Requires-Dist: pfeed (>=0.0.4,<0.1.0)
Requires-Dist: pfeed[core] (>=0.0.4,<0.1.0) ; extra == "core"
Requires-Dist: psutil (>=7.0.0,<8.0.0) ; extra == "core"
Requires-Dist: pyzmq (>=26.4.0,<27.0.0) ; extra == "core"
Requires-Dist: unitycatalog-ai (>=0.3.0,<0.4.0) ; extra == "core"
Requires-Dist: unitycatalog-client (>=0.2.1,<0.3.0) ; extra == "core"
Requires-Dist: wandb (>=0.19.9,<0.20.0) ; extra == "core"
Requires-Dist: weave (>=0.51.41,<0.52.0) ; extra == "core"
Project-URL: Documentation, https://mtflow-docs.pfund.ai
Project-URL: Homepage, https://pfund.ai
Project-URL: Repository, https://github.com/PFund-Software-Ltd/mtflow
